tract/__init__.py
tract/bindings.py
tract/fact.py
tract/inference_model.py
tract/model.py
tract/nnef.py
tract/onnx.py
tract/runnable.py
tract/state.py
tract/tract.pypy37-pp73-x86_64-linux-gnu.so
tract/value.py
tract-0.21.13.dist-info/METADATA
tract-0.21.13.dist-info/WHEEL
tract-0.21.13.dist-info/top_level.txt
tract-0.21.13.dist-info/RECORD
