Metadata-Version: 2.1
Name: tract
Version: 0.21.13
Summary: Python bindings for tract, a neural network inference engine
Author: Mathieu Poumeyrol, Sonos, and tract contributors
Author-email: mathieu@poumeyrol.fr
License: Apache License, Version 2.0 OR MIT
Project-URL: Documentation, https://sonos.github.io/tract
Project-URL: Source, https://github.com/sonos/tract
Keywords: onnx tensorflow nnef runtime neural network
Classifier: Programming Language :: Python :: 3
Classifier: Programming Language :: Python :: 3.7
Classifier: Programming Language :: Python :: 3.8
Classifier: Programming Language :: Python :: 3.9
Classifier: Programming Language :: Python :: 3.10
Classifier: Programming Language :: Python :: 3.11
Classifier: Programming Language :: Rust
Classifier: Topic :: Scientific/Engineering :: Mathematics
Classifier: Topic :: Scientific/Engineering :: Artificial Intelligence
Classifier: License :: OSI Approved :: Apache Software License
Classifier: License :: OSI Approved :: MIT License
Requires-Python: >=3.7
Requires-Dist: numpy
Provides-Extra: test
Requires-Dist: pytest ; extra == 'test'
